sumo_experiments/__init__.py
sumo_experiments/components/__init__.py
sumo_experiments/components/detectors.py
sumo_experiments/components/flows.py
sumo_experiments/components/infrastructures.py
sumo_experiments/preset_networks/__init__.py
sumo_experiments/preset_networks/artificial_preset_network.py
sumo_experiments/preset_networks/bologna_network.py
sumo_experiments/preset_networks/grid_network.py
sumo_experiments/preset_networks/intersection_network.py
sumo_experiments/preset_networks/lille_network.py
sumo_experiments/preset_networks/line_network.py
sumo_experiments/preset_networks/network.py
sumo_experiments/preset_networks/bologna/acosta/acosta.rou.xml
sumo_experiments/preset_networks/bologna/acosta/acosta_11569.rou.xml
sumo_experiments/preset_networks/bologna/acosta/acosta_12853.rou.xml
sumo_experiments/preset_networks/bologna/acosta/acosta_18093.rou.xml
sumo_experiments/preset_networks/bologna/acosta/acosta_18597.rou.xml
sumo_experiments/preset_networks/bologna/acosta/acosta_20713.rou.xml
sumo_experiments/preset_networks/bologna/acosta/acosta_21088.rou.xml
sumo_experiments/preset_networks/bologna/acosta/acosta_21263.rou.xml
sumo_experiments/preset_networks/bologna/acosta/acosta_26705.rou.xml
sumo_experiments/preset_networks/bologna/acosta/acosta_28200.rou.xml
sumo_experiments/preset_networks/bologna/acosta/acosta_29981.rou.xml
sumo_experiments/preset_networks/bologna/acosta/acosta_3008.rou.xml
sumo_experiments/preset_networks/bologna/acosta/acosta_30325.rou.xml
sumo_experiments/preset_networks/bologna/acosta/acosta_33246.rou.xml
sumo_experiments/preset_networks/bologna/acosta/acosta_47190.rou.xml
sumo_experiments/preset_networks/bologna/acosta/acosta_47724.rou.xml
sumo_experiments/preset_networks/bologna/acosta/acosta_48697.rou.xml
sumo_experiments/preset_networks/bologna/acosta/acosta_4915.rou.xml
sumo_experiments/preset_networks/bologna/acosta/acosta_49523.rou.xml
sumo_experiments/preset_networks/bologna/acosta/acosta_50144.rou.xml
sumo_experiments-5.5.0.dist-info/METADATA
sumo_experiments-5.5.0.dist-info/WHEEL
sumo_experiments-5.5.0.dist-info/licenses/AUTHORS.md
sumo_experiments-5.5.0.dist-info/licenses/LICENSE
sumo_experiments-5.5.0.dist-info/RECORD
