Metadata-Version: 2.4
Name: sumo-experiments
Version: 5.5.0
Summary: The sumo-experiments library implements a python interface for the Simulation of Urban MObility (SUMO) software.
Project-URL: Homepage, https://github.com/cristal-smac/sumo-experiments
Project-URL: Bug Tracker, https://github.com/cristal-smac/sumo-experiments/issues
Author-email: Jules Bompard <jules.bompard.etu@univ-lille.fr>, Antoine Nongaillard <antoine.nongaillard@univ-lille.fr>, Philippe Mathieu <philippe.mathieu@univ-lille.fr>
License:                   GNU LESSER GENERAL PUBLIC LICENSE
License-File: AUTHORS.md
License-File: LICENSE
Classifier: Development Status :: 3 - Alpha
Classifier: Environment :: X11 Applications :: Gnome
Classifier: License :: OSI Approved :: GNU Lesser General Public License v2 or later (LGPLv2+)
Classifier: Operating System :: POSIX :: Linux
Classifier: Programming Language :: Python :: 3
Classifier: Topic :: Scientific/Engineering :: Artificial Intelligence
Classifier: Topic :: Scientific/Engineering :: Interface Engine/Protocol Translator
Requires-Python: >=3.9
Requires-Dist: libsumo<2,>=1.24.0
Requires-Dist: networkx<4,>=3.3
Requires-Dist: numpy<3,>=1.26.0
Requires-Dist: pandas<3,>=2.1.1
Requires-Dist: torch<3,>=2.9.0
Requires-Dist: traci<2,>=1.18.0
